butch_filename_substring_remover/__init__.py
butch_filename_substring_remover/main.py
butch_filename_substring_remover/rename.py
butch_filename_substring_remover/rename_directory.py
butch_filename_substring_remover/utils.py
butch_filename_substring_remover-0.1.3.dist-info/LICENSE
butch_filename_substring_remover-0.1.3.dist-info/METADATA
butch_filename_substring_remover-0.1.3.dist-info/WHEEL
butch_filename_substring_remover-0.1.3.dist-info/entry_points.txt
butch_filename_substring_remover-0.1.3.dist-info/top_level.txt
butch_filename_substring_remover-0.1.3.dist-info/RECORD
