Metadata-Version: 2.1
Name: butch_filename_substring_remover
Version: 0.1.3
Summary: A batch renaming script to remove substrings from filenames and directories.
Home-page: https://github.com/namebogsecret/butch_filename_substring_remover
Author: Vladimir Podlevskikh
Author-email: Vladimir Podlevskikh <pypi@podlevskikh.com>
Project-URL: Homepage, https://github.com/namebogsecret/butch_filename_substring_remover
Project-URL: Issues, https://github.com/namebogsecret/butch_filename_substring_remover/issues
Classifier: Programming Language :: Python :: 3
Classifier: License :: OSI Approved :: MIT License
Classifier: Operating System :: OS Independent
Requires-Python: >=3.8
License-File: LICENSE
